docs/source/conf.py
indicate/__init__.py
indicate/decoder.py
indicate/encoder.py
indicate/hindi2english.py
indicate/logging.py
indicate/transliterate.py
indicate/utils.py
indicate/data/get_affidavits/crawler/__init__.py
indicate/data/get_affidavits/crawler/items.py
indicate/data/get_affidavits/crawler/middlewares.py
indicate/data/get_affidavits/crawler/pipelines.py
indicate/data/get_affidavits/crawler/settings.py
indicate/data/get_affidavits/crawler/spiders/__init__.py
indicate/data/get_affidavits/crawler/spiders/crawler_spider.py
indicate/data/get_espncricinfo/find_hindi_scorecards.py
indicate/data/get_espncricinfo/parse_hindi_scorecards.py
indicate/data/model/hindi_to_english/english_tokens.json
indicate/data/model/hindi_to_english/hindi_tokens.json
indicate/data/model/hindi_to_english/saved_weights/decoder.weights.h5
indicate/data/model/hindi_to_english/saved_weights/encoder.weights.h5
indicate/notebooks/Data_Preparation.ipynb
indicate/notebooks/Inference.ipynb
indicate/notebooks/Inference_latest.ipynb
indicate/notebooks/Train.ipynb
indicate/notebooks/Train_latest.ipynb
indicate/notebooks/Transliterate.ipynb
indicate/notebooks/transliterate_cricket.ipynb
indicate/tests/__init__.py
indicate/tests/test_010_hindi_translate.py
indicate-0.3.1.dist-info/licenses/LICENSE
indicate-0.3.1.dist-info/METADATA
indicate-0.3.1.dist-info/WHEEL
indicate-0.3.1.dist-info/entry_points.txt
indicate-0.3.1.dist-info/top_level.txt
indicate-0.3.1.dist-info/RECORD
