Metadata-Version: 2.4
Name: indicate
Version: 0.3.1
Summary: Transliterations to/from Indian languages
Author-email: Rajashekar Chintalapati <rajshekar.ch@gmail.com>, Gaurav Sood <gsood07@gmail.com>
License: MIT
Project-URL: Homepage, https://github.com/in-rolls/indicate
Project-URL: Repository, https://github.com/in-rolls/indicate
Keywords: transliterate,indic,hindi,english
Classifier: Development Status :: 3 - Alpha
Classifier: Intended Audience :: Developers
Classifier: License :: OSI Approved :: MIT License
Classifier: Programming Language :: Python :: 3.8
Classifier: Programming Language :: Python :: 3.9
Classifier: Programming Language :: Python :: 3.10
Classifier: Programming Language :: Python :: 3.11
Classifier: Programming Language :: Python :: 3.12
Classifier: Topic :: Scientific/Engineering :: Information Analysis
Classifier: Topic :: Software Development :: Libraries :: Python Modules
Classifier: Topic :: Utilities
Requires-Python: >=3.8
License-File: LICENSE
Requires-Dist: tqdm
Requires-Dist: func-timeout
Requires-Dist: tensorflow<3.0.0,>=2.18.0
Requires-Dist: importlib-resources>=5.0.0; python_version < "3.9"
Provides-Extra: dev
Requires-Dist: black>=23.0.0; extra == "dev"
Requires-Dist: isort>=5.12.0; extra == "dev"
Requires-Dist: flake8>=6.0.0; extra == "dev"
Requires-Dist: mypy>=1.0.0; extra == "dev"
Requires-Dist: pytest>=7.0.0; extra == "dev"
Requires-Dist: pytest-cov>=4.0.0; extra == "dev"
Requires-Dist: pre-commit>=3.0.0; extra == "dev"
Requires-Dist: check-manifest; extra == "dev"
Provides-Extra: test
Requires-Dist: coverage; extra == "test"
Requires-Dist: tox; extra == "test"
Dynamic: license-file
